apiclient/__init__.py
googleapiclient/__init__.py
googleapiclient/_auth.py
googleapiclient/_helpers.py
googleapiclient/channel.py
googleapiclient/discovery.py
googleapiclient/errors.py
googleapiclient/http.py
googleapiclient/mimeparse.py
googleapiclient/model.py
googleapiclient/sample_tools.py
googleapiclient/schema.py
googleapiclient/version.py
googleapiclient/discovery_cache/__init__.py
googleapiclient/discovery_cache/appengine_memcache.py
googleapiclient/discovery_cache/base.py
googleapiclient/discovery_cache/file_cache.py
googleapiclient/discovery_cache/documents/abusiveexperiencereport.v1.json
googleapiclient/discovery_cache/documents/acceleratedmobilepageurl.v1.json
googleapiclient/discovery_cache/documents/accessapproval.v1.json
googleapiclient/discovery_cache/documents/accesscontextmanager.v1.json
googleapiclient/discovery_cache/documents/accesscontextmanager.v1beta.json
googleapiclient/discovery_cache/documents/acmedns.v1.json
googleapiclient/discovery_cache/documents/addressvalidation.v1.json
googleapiclient/discovery_cache/documents/adexchangebuyer.v1.2.json
googleapiclient/discovery_cache/documents/adexchangebuyer.v1.3.json
googleapiclient/discovery_cache/documents/adexchangebuyer.v1.4.json
googleapiclient/discovery_cache/documents/adexchangebuyer2.v2beta1.json
googleapiclient/discovery_cache/documents/adexperiencereport.v1.json
googleapiclient/discovery_cache/documents/admin.datatransfer_v1.json
googleapiclient/discovery_cache/documents/admin.datatransferv1.json
googleapiclient/discovery_cache/documents/admin.directory_v1.json
googleapiclient/discovery_cache/documents/admin.directoryv1.json
googleapiclient/discovery_cache/documents/admin.reports_v1.json
googleapiclient/discovery_cache/documents/admin.reportsv1.json
googleapiclient/discovery_cache/documents/admob.v1.json
googleapiclient/discovery_cache/documents/admob.v1beta.json
googleapiclient/discovery_cache/documents/adsense.v2.json
googleapiclient/discovery_cache/documents/adsensehost.v4.1.json
google_api_python_client-2.150.0.dist-info/LICENSE
google_api_python_client-2.150.0.dist-info/METADATA
google_api_python_client-2.150.0.dist-info/WHEEL
google_api_python_client-2.150.0.dist-info/top_level.txt
google_api_python_client-2.150.0.dist-info/RECORD
