Metadata-Version: 2.1
Name: google-api-python-client
Version: 2.150.0
Summary: Google API Client Library for Python
Home-page: https://github.com/googleapis/google-api-python-client/
Author: Google LLC
Author-email: googleapis-packages@google.com
License: Apache 2.0
Keywords: google api client
Classifier: Programming Language :: Python :: 3
Classifier: Programming Language :: Python :: 3.7
Classifier: Programming Language :: Python :: 3.8
Classifier: Programming Language :: Python :: 3.9
Classifier: Programming Language :: Python :: 3.10
Classifier: Programming Language :: Python :: 3.11
Classifier: Programming Language :: Python :: 3.12
Classifier: Development Status :: 5 - Production/Stable
Classifier: Intended Audience :: Developers
Classifier: License :: OSI Approved :: Apache Software License
Classifier: Operating System :: OS Independent
Classifier: Topic :: Internet :: WWW/HTTP
Requires-Python: >=3.7
License-File: LICENSE
Requires-Dist: httplib2<1.dev0,>=0.19.0
Requires-Dist: google-auth!=2.24.0,!=2.25.0,<3.0.0.dev0,>=1.32.0
Requires-Dist: google-auth-httplib2<1.0.0,>=0.2.0
Requires-Dist: google-api-core!=2.0.*,!=2.1.*,!=2.2.*,!=2.3.0,<3.0.0.dev0,>=1.31.5
Requires-Dist: uritemplate<5,>=3.0.1
